{
  "heuteWichtig max 4 Felder": [
    "Waldeck bitte heute Abend dran denken das Tor abzuschließen.",
    "Nächste Woche fahren wir zur Ausstellung, nehmt Eure Westen mit, anziehen auf der Ausstellung",
    "Vergesst nicht nach Öl und Wasser zu schauen, Daumen hoch wenn erledigt."
  ],
  "daueranzeige": [
    ".",
    " .",
    ".",
    "."
  ],
  "langzeitInfo": [
    "Osterferien für unser Betrieb ist vom 02.04.2026 bis 07.04.2026 einschließlich, Am 08.04.2026 sind alle wieder da",
    "Sommerferien sind ab den 13.07.2026 geplant für 3 Wochen, (keine feste Zusage)",
    "Ab 30.03.2026 2 Wochen Lärmschutz auf Borkum.---Środki ochrony przed hałasem będą obowiązywać na wyspie Borkum przez dwa tygodnie, począwszy od 26 marca 2026 r."
  ],
  "ticker": [
    "Wir wünschen Euch ein schönes Wochenende  ---   Życzymy Wam cudownego weekendu!"
  ],
  "heuteWichtig": [
    "Guten Morgen Leute, gut das Ihr da seid",
    "Dzień dobry wszystkim, cieszę się, że tu jesteście!",
    "Heute soll es trocken bleiben, nur am Anfang etwas regen vielleicht",
    "Dziś pogoda powinna być sucha, na początku może jedynie lekko popadać."
  ],
  "daueranzeigeBild": "/uploads/2021_menne_156.jpg"
}
